cmsis_stream/__init__.py
cmsis_stream/cg/__init__.py
cmsis_stream/cg/events.py
cmsis_stream/cg/types.py
cmsis_stream/cg/nodes/CFFT.py
cmsis_stream/cg/nodes/Duplicate.py
cmsis_stream/cg/nodes/ICFFT.py
cmsis_stream/cg/nodes/InterleavedStereoToMono.py
cmsis_stream/cg/nodes/MFCC.py
cmsis_stream/cg/nodes/NullSink.py
cmsis_stream/cg/nodes/ToComplex.py
cmsis_stream/cg/nodes/ToReal.py
cmsis_stream/cg/nodes/Unzip.py
cmsis_stream/cg/nodes/Zip.py
cmsis_stream/cg/nodes/__init__.py
cmsis_stream/cg/nodes/simu.py
cmsis_stream/cg/nodes/host/FileSink.py
cmsis_stream/cg/nodes/host/FileSource.py
cmsis_stream/cg/nodes/host/NumpySink.py
cmsis_stream/cg/nodes/host/VHT.py
cmsis_stream/cg/nodes/host/VHTCGSTATIC.py
cmsis_stream/cg/nodes/host/WavSink.py
cmsis_stream/cg/nodes/host/WavSource.py
cmsis_stream/cg/nodes/host/__init__.py
cmsis_stream/cg/nodes/host/message.py
cmsis_stream/cg/scheduler/__init__.py
cmsis_stream/cg/scheduler/args.py
cmsis_stream/cg/scheduler/ccode.py
cmsis_stream/cg/scheduler/config.py
cmsis_stream/cg/scheduler/description.py
cmsis_stream/cg/scheduler/graphviz.py
cmsis_stream/cg/scheduler/node.py
cmsis_stream/cg/scheduler/standard.py
cmsis_stream/cg/scheduler/templates/cmsis.cpp
cmsis_stream/cg/scheduler/templates/cmsisCheck.cpp
cmsis_stream/cg/scheduler/templates/code.cpp
cmsis_stream/cg/scheduler/templates/code.h
cmsis_stream/cg/scheduler/templates/codeSwitch.cpp
cmsis_stream/cg/scheduler/templates/commonc.cpp
cmsis_stream/cg/scheduler/templates/defineConfig.h
cmsis_stream/cg/scheduler/templates/dot_template.dot
cmsis_stream/cg/scheduler/templates/precompute_dot_template.dot
cmsis_stream/cg/sds/__init__.py
cmsis_stream/cg/sds/sds_nodes.py
cmsis_stream/cg/yaml/__init__.py
cmsis_stream/cg/yaml/exportyaml.py
cmsis_stream/cg/yaml/importyaml.py
cmsis_stream-3.1.0.dist-info/licenses/LICENSE.txt
cmsis_stream-3.1.0.dist-info/METADATA
cmsis_stream-3.1.0.dist-info/WHEEL
cmsis_stream-3.1.0.dist-info/top_level.txt
cmsis_stream-3.1.0.dist-info/RECORD
