Metadata-Version: 2.4
Name: cmsis-stream
Version: 3.1.0
Summary: CMSIS-Stream graph description
Home-page: https://github.com/ARM-software/CMSIS-Stream
Author: Copyright (C) 2023-2026 ARM Limited or its affiliates. All rights reserved.
Author-email: christophe.favergeon@arm.com
License: License :: OSI Approved :: Apache Software License
Project-URL: Bug Reports, https://github.com/ARM-software/CMSIS-Stream/issues
Project-URL: Source, https://github.com/ARM-software/CMSIS-Stream
Keywords: development,dsp,cmsis,CMSIS-Stream,Arm,signal processing,maths,ml,cortex-m,cortex-a
Platform: any
Classifier: Programming Language :: Python :: 3
Classifier: Programming Language :: Python :: Implementation :: CPython
Classifier: Programming Language :: C
Classifier: Operating System :: OS Independent
Classifier: Development Status :: 5 - Production/Stable
Classifier: Topic :: Software Development :: Embedded Systems
Classifier: Topic :: Scientific/Engineering :: Mathematics
Classifier: Environment :: Console
Classifier: Intended Audience :: Developers
Requires-Python: >=3.7
License-File: LICENSE.txt
Requires-Dist: networkx>=3.0
Requires-Dist: jinja2<4.0,>=3.1.2
Requires-Dist: sympy>=1.7.1
Requires-Dist: MarkupSafe<3.0,>=2.1.2
Requires-Dist: numpy
Requires-Dist: PyYAML>=6.0
Dynamic: author
Dynamic: author-email
Dynamic: classifier
Dynamic: description
Dynamic: description-content-type
Dynamic: home-page
Dynamic: keywords
Dynamic: license
Dynamic: license-file
Dynamic: platform
Dynamic: project-url
Dynamic: requires-dist
Dynamic: requires-python
Dynamic: summary
